timexy/__init__.py
timexy/language.py
timexy/languages/__init__.py
timexy/languages/de.py
timexy/languages/en.py
timexy/languages/fr.py
timexy/rule.py
timexy/timexy.py
timexy/util.py
timexy-0.1.3.dist-info/LICENSE
timexy-0.1.3.dist-info/WHEEL
timexy-0.1.3.dist-info/METADATA
timexy-0.1.3.dist-info/RECORD
