Metadata-Version: 2.1
Name: timexy
Version: 0.1.3
Summary: A spaCy custom component that extracts and normalizes dates and other temporal expressions
Home-page: https://github.com/paulrinckens/timexy
License: MIT
Keywords: python,spaCy,custom component,date time extraction,timex3
Author: Paul Rinckens
Maintainer: Paul Rinckens
Requires-Python: >=3.7,<4.0
Classifier: Development Status :: 4 - Beta
Classifier: Environment :: Console
Classifier: Environment :: MacOS X
Classifier: Intended Audience :: Developers
Classifier: Intended Audience :: Education
Classifier: Intended Audience :: Information Technology
Classifier: Intended Audience :: Science/Research
Classifier: License :: OSI Approved :: MIT License
Classifier: Operating System :: POSIX :: Linux
Classifier: Operating System :: Unix
Classifier: Programming Language :: Python :: 3
Classifier: Programming Language :: Python :: 3 :: Only
Classifier: Programming Language :: Python :: 3.10
Classifier: Programming Language :: Python :: 3.7
Classifier: Programming Language :: Python :: 3.8
Classifier: Programming Language :: Python :: 3.9
Classifier: Topic :: Scientific/Engineering
Classifier: Topic :: Scientific/Engineering :: Artificial Intelligence
Classifier: Topic :: Scientific/Engineering :: Information Analysis
Classifier: Topic :: Software Development
Classifier: Topic :: Software Development :: Libraries
Classifier: Topic :: Software Development :: Libraries :: Python Modules
Requires-Dist: spacy (>=3.2.2,<4.0.0)
Project-URL: Documentation, https://github.com/paulrinckens/timexy#readme
Project-URL: Repository, https://github.com/paulrinckens/timexy
